MANIFEST.in
README.txt
requirements.txt
setup.py
bcbiocov/__init__.py
bcbiocov/basic.py
bcbiocov/bias.py
bcbiocov/fastqc.py
bcbiocov/manage.py
bcbiocov/prepare.py
bcbiocov/report.Rmd
bcbiocov/select.py
bcbiocov/total.py
bcbiocov/variants.py
bcbiocov.egg-info/PKG-INFO
bcbiocov.egg-info/SOURCES.txt
bcbiocov.egg-info/dependency_links.txt
bcbiocov.egg-info/not-zip-safe
bcbiocov.egg-info/requires.txt
bcbiocov.egg-info/top_level.txt
scripts/coverage.py