Metadata-Version: 1.1
Name: bcbiocov
Version: 0.99.4
Summary: exome coverage calculation
Home-page: UNKNOWN
Author: Lorena Pantano
Author-email: lpantano@iscb.org
License: MIT
Keywords: custom pipelines
Platform: UNKNOWN
Classifier: Development Status :: 3 - Alpha
Classifier: License :: OSI Approved :: MIT License
Classifier: Programming Language :: Python :: 2.7
Classifier: Topic :: Scientific/Engineering :: Bio-Informatics
